README.rst
setup.py
parser/__init__.py
parser/core.py
parser/helpers.py
parser_shenghui.egg-info/PKG-INFO
parser_shenghui.egg-info/SOURCES.txt
parser_shenghui.egg-info/dependency_links.txt
parser_shenghui.egg-info/top_level.txt
tests/__init__.py
tests/context.py
tests/test_advanced.py
tests/test_basic.py
tests/test_document_scan.py
tests/test_duplicate.py