Metadata-Version: 1.0
Name: parser-shenghui
Version: 0.1.0
Summary: TRI Coding Challenge.
Home-page: UNKNOWN
Author: Shenghui Sun
Author-email: hui.sunny.sun@gmail.com
License: UNKNOWN
Platform: UNKNOWN
